MANIFEST.in
README.md
setup.cfg
setup.py
sudokugridgen/__init__.py
sudokugridgen/gen.py
sudokugridgen.egg-info/PKG-INFO
sudokugridgen.egg-info/SOURCES.txt
sudokugridgen.egg-info/dependency_links.txt
sudokugridgen.egg-info/not-zip-safe
sudokugridgen.egg-info/top_level.txt