Metadata-Version: 1.0
Name: sudokugridgen
Version: 0.1
Summary: a sudoku grid generator
Home-page: http://github.com/georgercarder/sudokugridgen
Author: George Carder
Author-email: georgercarder@gmail.com
License: MIT
Platform: UNKNOWN
